fabric/analytics/environment/notebook_plugin/__init__.py
fabric/analytics/environment/notebook_plugin/context.py
fabric/analytics/environment/notebook_plugin/log_handlers.py
fabric/analytics/environment/notebook_plugin/token_service_client.py
fabric/analytics/environment/notebook_plugin/utils.py
fabric/analytics/environment/notebook_plugin/python_notebook_plugin/__init__.py
fabric/analytics/environment/notebook_plugin/python_notebook_plugin/context.py
fabric/analytics/environment/notebook_plugin/python_notebook_plugin/credentials.py
fabric/analytics/environment/notebook_plugin/python_notebook_plugin/mwc_token_credentials.py
fabric/analytics/environment/notebook_plugin/spark_notebook_plugin/__init__.py
fabric/analytics/environment/notebook_plugin/spark_notebook_plugin/context.py
fabric/analytics/environment/notebook_plugin/spark_notebook_plugin/credentials.py
fabric/analytics/environment/notebook_plugin/spark_notebook_plugin/mwc_token_credentials.py
fabric_analytics_notebook_plugin-0.0.3.dist-info/licenses/LICENSE.txt
fabric_analytics_notebook_plugin-0.0.3.dist-info/METADATA
fabric_analytics_notebook_plugin-0.0.3.dist-info/WHEEL
fabric_analytics_notebook_plugin-0.0.3.dist-info/entry_points.txt
fabric_analytics_notebook_plugin-0.0.3.dist-info/top_level.txt
fabric_analytics_notebook_plugin-0.0.3.dist-info/RECORD
