Metadata-Version: 2.4
Name: fabric-analytics-notebook-plugin
Version: 0.0.3
Summary: Plugin for FABRIC SDK, used in fabric online Spark/Python Notebook and SJD
Author: Microsoft Corporation
License: MICROSOFT SOFTWARE LICENSE TERMS
Classifier: Development Status :: 3 - Alpha
Classifier: Intended Audience :: Developers
Classifier: Intended Audience :: Education
Classifier: Intended Audience :: Science/Research
Classifier: Programming Language :: Python :: 3.10
Classifier: Programming Language :: Python :: 3 :: Only
Requires-Python: <3.15,>=3.10
License-File: LICENSE.txt
Requires-Dist: psutil
Requires-Dist: azure-core
Requires-Dist: azure-identity
Requires-Dist: synapseml-utils
Requires-Dist: fabric-analytics-sdk>=0.0.3
Provides-Extra: test
Provides-Extra: dev
Requires-Dist: black[jupyter]; extra == "dev"
Dynamic: license-file
